liang_utils/__init__.py
liang_utils/match_dict.py
liang_utils/process_log.py
liang_utils-1.2.1.dist-info/METADATA
liang_utils-1.2.1.dist-info/WHEEL
liang_utils-1.2.1.dist-info/entry_points.txt
liang_utils-1.2.1.dist-info/top_level.txt
liang_utils-1.2.1.dist-info/RECORD
