Metadata-Version: 2.1
Name: liang-utils
Version: 1.2.1
Summary: A couple of liang_utils for network automation
Author: Liang
Requires-Python: >=3.8
Requires-Dist: ttp
Requires-Dist: tqdm
